{
	"schemaVersion": 1,
	"id": "minecart_experiment_changes",
	"version": "${version}",
	"name": "Minecart Experimental Changes",
	"description": "Merging the minecart experiment with some non-experimental 'features'",
	"authors": [
		"LindonKelley"
	],
	"contact": {
		"homepage": "https://github.com/LindonKelley/minecart-experiment-changes",
		"sources": "https://github.com/LindonKelley/minecart-experiment-changes"
	},
	"license": "GPL-3.0-or-later",
	"icon": "assets/minecart_experiment_changes/icon.png",
	"environment": "*",
	"entrypoints": {
		"main": [
			"io.github.lindonkelley.MinecartExperimentChanges"
		]
	},
	"mixins": [
		"minecart_experiment_changes.mixins.json"
	],
	"depends": {
		"fabricloader": ">=0.16.10",
		"minecraft": "~1.21.4",
		"java": ">=21",
		"fabric-api": "*"
	},
	"suggests": {
		"another-mod": "*"
	},
	"accessWidener": "minecart_experiment_changes.accesswidener"
}